Metadata-Version: 1.0
Name: GnB-distributions-project
Version: 0.1
Summary: Gaussian and binomial distributions
Home-page: UNKNOWN
Author: Desmond Webb
Author-email: datasciencedjw@gmail.com
License: UNKNOWN
Platform: UNKNOWN
